{
    "id": "cult_leader",
    "name":"Cult Leader",
    "description":"Each night, you become the alignment of an alive neighbour. If all good players choose to join your cult, your team wins.",
    "alignment":"GOOD",
    "class":"TOWN",
    "tokens":[],
    "first_night_desc":"If the cult leader changed alignment, show them the thumbs up good signal of the thumbs down evil signal accordingly.",
    "other_night_desc":"If the cult leader changed alignment, show them the thumbs up good signal of the thumbs down evil signal accordingly.",
    "change_makeup":[],
    "hide_token":false,
    "hide_face":true
}